{"slug":"bills_with_nlp","name":"bills_with_nlp","description":"Using NLP and ML for looking at legislative bill data","url":"https://github.com/matthewdeanmartin/bills_with_nlp","repository_url":"https://github.com/matthewdeanmartin/bills_with_nlp","tags":[],"featured":false,"status":"archived","cms":{"suppress":false,"package_links":[]},"related_skills":[],"_links":[{"rel":"self","href":"/apis/projects/by-slug/bills_with_nlp.json","type":"application/json"},{"rel":"collection","href":"/apis/projects/index.json","type":"application/json"},{"rel":"first","href":"/apis/projects/pages/1.json","type":"application/json"},{"rel":"describedby","href":"/apis/openapi.yaml","type":"text/yaml"}],"_rels":{"pypi_packages":[]}}