{"slug":"isopod_js","name":"isopod_js","description":"Trivial adventure game to learn about build scripts for Plain js and HTML","url":"https://github.com/matthewdeanmartin/isopod_js","repository_url":"https://github.com/matthewdeanmartin/isopod_js","tags":[],"primary_language":"JavaScript","featured":false,"status":"archived","cms":{"suppress":false,"package_links":[]},"related_skills":[],"_links":[{"rel":"self","href":"/apis/projects/by-slug/isopod_js.json","type":"application/json"},{"rel":"collection","href":"/apis/projects/index.json","type":"application/json"},{"rel":"first","href":"/apis/projects/pages/1.json","type":"application/json"},{"rel":"describedby","href":"/apis/openapi.yaml","type":"text/yaml"}],"_rels":{"pypi_packages":[]}}