{"slug":"metametameta","name":"metametameta","description":"Generate dunder metadata file with __title__, __author__, etc. Also tools to discover these in other packages.","url":"https://matthewdeanmartin.github.io/metametameta/metametameta/index.html","repository_url":"https://github.com/matthewdeanmartin/metametameta","tags":["python","python-metadata"],"featured":false,"status":"active","cms":{"suppress":false,"package_links":[]},"related_skills":[],"_links":[{"rel":"self","href":"/apis/projects/by-slug/metametameta.json","type":"application/json"},{"rel":"collection","href":"/apis/projects/index.json","type":"application/json"},{"rel":"first","href":"/apis/projects/pages/1.json","type":"application/json"},{"rel":"describedby","href":"/apis/openapi.yaml","type":"text/yaml"}],"_rels":{"pypi_packages":[{"ref":"/apis/pypi/by-name/metametameta.json","rel":"related"}]}}